[
  {
    "departureTerminalId": "0001",
    "arrivalTerminalId": "5012",
    "durationInMinutes": [
      210
    ],
    "operator": [
      "대원고속"
    ],
    "departureTime": {
      "hour": 7,
      "minute": 30
    },
    "isTemporaryRoute": false,
    "fare": {
      "어른": [
        35300
      ],
      "초등생": [
        17700
      ],
      "중고생": [
        24700
      ]
    },
    "stops": [
      [
        {
          "name": "동서울"
        },
        {
          "name": "일직"
        },
        {
          "name": "단촌"
        },
        {
          "name": "의성"
        },
        {
          "name": "도리원"
        },
        {
          "name": "군위"
        }
      ]
    ],
    "type": "bus",
    "extra": {
      "seatsAmount": [
        28
      ],
      "busClass": [
        "시외우등"
      ]
    },
    "routeId": "000001501201",
    "pattern": {
      "type": "irregular",
      "fixedDays": [
        6,
        7
      ],
      "irregularDays": [
        1,
        2,
        3,
        4,
        5
      ]
    }
  },
  {
    "departureTerminalId": "0001",
    "arrivalTerminalId": "5012",
    "durationInMinutes": [
      210
    ],
    "operator": [
      "대원고속"
    ],
    "departureTime": {
      "hour": 12,
      "minute": 30
    },
    "isTemporaryRoute": false,
    "fare": {
      "어른": [
        35300
      ],
      "초등생": [
        17700
      ],
      "중고생": [
        24700
      ]
    },
    "stops": [
      [
        {
          "name": "동서울"
        },
        {
          "name": "일직"
        },
        {
          "name": "단촌"
        },
        {
          "name": "의성"
        },
        {
          "name": "도리원"
        },
        {
          "name": "군위"
        }
      ]
    ],
    "type": "bus",
    "extra": {
      "seatsAmount": [
        28
      ],
      "busClass": [
        "시외우등"
      ]
    },
    "routeId": "000001501201",
    "pattern": {
      "type": "irregular",
      "fixedDays": [
        6,
        7
      ],
      "irregularDays": [
        1,
        2,
        3,
        4,
        5
      ]
    }
  },
  {
    "departureTerminalId": "0001",
    "arrivalTerminalId": "5012",
    "durationInMinutes": [
      210
    ],
    "operator": [
      "대원고속"
    ],
    "departureTime": {
      "hour": 15,
      "minute": 40
    },
    "isTemporaryRoute": false,
    "fare": {
      "어른": [
        35300
      ],
      "초등생": [
        17700
      ],
      "중고생": [
        24700
      ]
    },
    "stops": [
      [
        {
          "name": "동서울"
        },
        {
          "name": "일직"
        },
        {
          "name": "단촌"
        },
        {
          "name": "의성"
        },
        {
          "name": "도리원"
        },
        {
          "name": "군위"
        }
      ]
    ],
    "type": "bus",
    "extra": {
      "seatsAmount": [
        28
      ],
      "busClass": [
        "시외우등"
      ]
    },
    "routeId": "000001501201",
    "pattern": {
      "type": "irregular",
      "fixedDays": [
        6,
        7
      ],
      "irregularDays": [
        1,
        2,
        3,
        4,
        5
      ]
    }
  },
  {
    "departureTerminalId": "0001",
    "arrivalTerminalId": "5012",
    "durationInMinutes": [
      210
    ],
    "operator": [
      "대원고속"
    ],
    "departureTime": {
      "hour": 17,
      "minute": 30
    },
    "isTemporaryRoute": false,
    "fare": {
      "어른": [
        35300
      ],
      "초등생": [
        17700
      ],
      "중고생": [
        24700
      ]
    },
    "stops": [
      [
        {
          "name": "동서울"
        },
        {
          "name": "일직"
        },
        {
          "name": "단촌"
        },
        {
          "name": "의성"
        },
        {
          "name": "도리원"
        },
        {
          "name": "군위"
        }
      ]
    ],
    "type": "bus",
    "extra": {
      "seatsAmount": [
        28
      ],
      "busClass": [
        "시외우등"
      ]
    },
    "routeId": "000001501201",
    "pattern": {
      "type": "irregular",
      "fixedDays": [
        6,
        7
      ],
      "irregularDays": [
        1,
        2,
        3,
        4,
        5
      ]
    }
  }
]