[
  {
    "departureTerminalId": "1807",
    "arrivalTerminalId": "0004",
    "durationInMinutes": [
      0
    ],
    "operator": [
      "대원고속"
    ],
    "departureTime": {
      "hour": 6,
      "minute": 10
    },
    "isTemporaryRoute": false,
    "fare": {
      "어른": [
        7500
      ],
      "초등생": [
        3800
      ],
      "중고생": [
        5300
      ]
    },
    "stops": [
      [
        {
          "name": "안중"
        },
        {
          "name": "안중오거리"
        },
        {
          "name": "숙성리"
        },
        {
          "name": "태평아파트"
        },
        {
          "name": "평택"
        },
        {
          "name": "평택대"
        },
        {
          "name": "용이동"
        },
        {
          "name": "서울남부"
        }
      ]
    ],
    "type": "bus",
    "extra": {
      "seatsAmount": [
        40
      ],
      "busClass": [
        "일반"
      ]
    },
    "routeId": "101052000406",
    "pattern": {
      "type": "irregular",
      "fixedDays": [
        4,
        5,
        6,
        7
      ],
      "irregularDays": [
        1,
        2,
        3
      ]
    }
  },
  {
    "departureTerminalId": "1807",
    "arrivalTerminalId": "0004",
    "durationInMinutes": [
      0
    ],
    "operator": [
      "대원고속"
    ],
    "departureTime": {
      "hour": 6,
      "minute": 50
    },
    "isTemporaryRoute": false,
    "fare": {
      "어른": [
        7500
      ],
      "초등생": [
        3800
      ],
      "중고생": [
        5300
      ]
    },
    "stops": [
      [
        {
          "name": "안중"
        },
        {
          "name": "안중오거리"
        },
        {
          "name": "숙성리"
        },
        {
          "name": "태평아파트"
        },
        {
          "name": "평택"
        },
        {
          "name": "평택대"
        },
        {
          "name": "용이동"
        },
        {
          "name": "서울남부"
        }
      ]
    ],
    "type": "bus",
    "extra": {
      "seatsAmount": [
        40
      ],
      "busClass": [
        "일반"
      ]
    },
    "routeId": "101052000406",
    "pattern": {
      "type": "irregular",
      "fixedDays": [
        4,
        5,
        6,
        7
      ],
      "irregularDays": [
        1,
        2,
        3
      ]
    }
  },
  {
    "departureTerminalId": "1807",
    "arrivalTerminalId": "0004",
    "durationInMinutes": [
      0
    ],
    "operator": [
      "대원고속"
    ],
    "departureTime": {
      "hour": 7,
      "minute": 40
    },
    "isTemporaryRoute": false,
    "fare": {
      "어른": [
        7500
      ],
      "초등생": [
        3800
      ],
      "중고생": [
        5300
      ]
    },
    "stops": [
      [
        {
          "name": "안중"
        },
        {
          "name": "안중오거리"
        },
        {
          "name": "숙성리"
        },
        {
          "name": "태평아파트"
        },
        {
          "name": "평택"
        },
        {
          "name": "평택대"
        },
        {
          "name": "용이동"
        },
        {
          "name": "서울남부"
        }
      ]
    ],
    "type": "bus",
    "extra": {
      "seatsAmount": [
        40
      ],
      "busClass": [
        "일반"
      ]
    },
    "routeId": "101052000406",
    "pattern": {
      "type": "irregular",
      "fixedDays": [
        4,
        5,
        6,
        7
      ],
      "irregularDays": [
        1,
        2,
        3
      ]
    }
  },
  {
    "departureTerminalId": "1807",
    "arrivalTerminalId": "0004",
    "durationInMinutes": [
      0
    ],
    "operator": [
      "대원고속"
    ],
    "departureTime": {
      "hour": 8,
      "minute": 20
    },
    "isTemporaryRoute": false,
    "fare": {
      "어른": [
        7500
      ],
      "초등생": [
        3800
      ],
      "중고생": [
        5300
      ]
    },
    "stops": [
      [
        {
          "name": "안중"
        },
        {
          "name": "안중오거리"
        },
        {
          "name": "숙성리"
        },
        {
          "name": "태평아파트"
        },
        {
          "name": "평택"
        },
        {
          "name": "평택대"
        },
        {
          "name": "용이동"
        },
        {
          "name": "서울남부"
        }
      ]
    ],
    "type": "bus",
    "extra": {
      "seatsAmount": [
        40
      ],
      "busClass": [
        "일반"
      ]
    },
    "routeId": "101052000406",
    "pattern": {
      "type": "irregular",
      "fixedDays": [
        4,
        5,
        6,
        7
      ],
      "irregularDays": [
        1,
        2,
        3
      ]
    }
  },
  {
    "departureTerminalId": "1807",
    "arrivalTerminalId": "0004",
    "durationInMinutes": [
      0
    ],
    "operator": [
      "대원고속"
    ],
    "departureTime": {
      "hour": 9,
      "minute": 20
    },
    "isTemporaryRoute": false,
    "fare": {
      "어른": [
        7500
      ],
      "초등생": [
        3800
      ],
      "중고생": [
        5300
      ]
    },
    "stops": [
      [
        {
          "name": "안중"
        },
        {
          "name": "안중오거리"
        },
        {
          "name": "숙성리"
        },
        {
          "name": "태평아파트"
        },
        {
          "name": "평택"
        },
        {
          "name": "평택대"
        },
        {
          "name": "용이동"
        },
        {
          "name": "서울남부"
        }
      ]
    ],
    "type": "bus",
    "extra": {
      "seatsAmount": [
        40
      ],
      "busClass": [
        "일반"
      ]
    },
    "routeId": "101052000406",
    "pattern": {
      "type": "irregular",
      "fixedDays": [
        4,
        5,
        6,
        7
      ],
      "irregularDays": [
        1,
        2,
        3
      ]
    }
  },
  {
    "departureTerminalId": "1807",
    "arrivalTerminalId": "0004",
    "durationInMinutes": [
      0
    ],
    "operator": [
      "대원고속"
    ],
    "departureTime": {
      "hour": 10,
      "minute": 10
    },
    "isTemporaryRoute": false,
    "fare": {
      "어른": [
        7500
      ],
      "초등생": [
        3800
      ],
      "중고생": [
        5300
      ]
    },
    "stops": [
      [
        {
          "name": "안중"
        },
        {
          "name": "안중오거리"
        },
        {
          "name": "숙성리"
        },
        {
          "name": "태평아파트"
        },
        {
          "name": "평택"
        },
        {
          "name": "평택대"
        },
        {
          "name": "용이동"
        },
        {
          "name": "서울남부"
        }
      ]
    ],
    "type": "bus",
    "extra": {
      "seatsAmount": [
        40
      ],
      "busClass": [
        "일반"
      ]
    },
    "routeId": "101052000406",
    "pattern": {
      "type": "irregular",
      "fixedDays": [
        4,
        5,
        6,
        7
      ],
      "irregularDays": [
        1,
        2,
        3
      ]
    }
  },
  {
    "departureTerminalId": "1807",
    "arrivalTerminalId": "0004",
    "durationInMinutes": [
      0
    ],
    "operator": [
      "대원고속"
    ],
    "departureTime": {
      "hour": 10,
      "minute": 50
    },
    "isTemporaryRoute": false,
    "fare": {
      "어른": [
        7500
      ],
      "초등생": [
        3800
      ],
      "중고생": [
        5300
      ]
    },
    "stops": [
      [
        {
          "name": "안중"
        },
        {
          "name": "안중오거리"
        },
        {
          "name": "숙성리"
        },
        {
          "name": "태평아파트"
        },
        {
          "name": "평택"
        },
        {
          "name": "평택대"
        },
        {
          "name": "용이동"
        },
        {
          "name": "서울남부"
        }
      ]
    ],
    "type": "bus",
    "extra": {
      "seatsAmount": [
        40
      ],
      "busClass": [
        "일반"
      ]
    },
    "routeId": "101052000406",
    "pattern": {
      "type": "irregular",
      "fixedDays": [
        4,
        5,
        6,
        7
      ],
      "irregularDays": [
        1,
        2,
        3
      ]
    }
  },
  {
    "departureTerminalId": "1807",
    "arrivalTerminalId": "0004",
    "durationInMinutes": [
      0
    ],
    "operator": [
      "대원고속"
    ],
    "departureTime": {
      "hour": 11,
      "minute": 30
    },
    "isTemporaryRoute": false,
    "fare": {
      "어른": [
        7500
      ],
      "초등생": [
        3800
      ],
      "중고생": [
        5300
      ]
    },
    "stops": [
      [
        {
          "name": "안중"
        },
        {
          "name": "안중오거리"
        },
        {
          "name": "숙성리"
        },
        {
          "name": "태평아파트"
        },
        {
          "name": "평택"
        },
        {
          "name": "평택대"
        },
        {
          "name": "용이동"
        },
        {
          "name": "서울남부"
        }
      ]
    ],
    "type": "bus",
    "extra": {
      "seatsAmount": [
        40
      ],
      "busClass": [
        "일반"
      ]
    },
    "routeId": "101052000406",
    "pattern": {
      "type": "irregular",
      "fixedDays": [
        4,
        5,
        6,
        7
      ],
      "irregularDays": [
        1,
        2,
        3
      ]
    }
  },
  {
    "departureTerminalId": "1807",
    "arrivalTerminalId": "0004",
    "durationInMinutes": [
      0
    ],
    "operator": [
      "대원고속"
    ],
    "departureTime": {
      "hour": 12,
      "minute": 10
    },
    "isTemporaryRoute": false,
    "fare": {
      "어른": [
        7500
      ],
      "초등생": [
        3800
      ],
      "중고생": [
        5300
      ]
    },
    "stops": [
      [
        {
          "name": "안중"
        },
        {
          "name": "안중오거리"
        },
        {
          "name": "숙성리"
        },
        {
          "name": "태평아파트"
        },
        {
          "name": "평택"
        },
        {
          "name": "평택대"
        },
        {
          "name": "용이동"
        },
        {
          "name": "서울남부"
        }
      ]
    ],
    "type": "bus",
    "extra": {
      "seatsAmount": [
        40
      ],
      "busClass": [
        "일반"
      ]
    },
    "routeId": "101052000406",
    "pattern": {
      "type": "irregular",
      "fixedDays": [
        4,
        5,
        6,
        7
      ],
      "irregularDays": [
        1,
        2,
        3
      ]
    }
  },
  {
    "departureTerminalId": "1807",
    "arrivalTerminalId": "0004",
    "durationInMinutes": [
      0
    ],
    "operator": [
      "대원고속"
    ],
    "departureTime": {
      "hour": 13,
      "minute": 10
    },
    "isTemporaryRoute": false,
    "fare": {
      "어른": [
        7500
      ],
      "초등생": [
        3800
      ],
      "중고생": [
        5300
      ]
    },
    "stops": [
      [
        {
          "name": "안중"
        },
        {
          "name": "안중오거리"
        },
        {
          "name": "숙성리"
        },
        {
          "name": "태평아파트"
        },
        {
          "name": "평택"
        },
        {
          "name": "평택대"
        },
        {
          "name": "용이동"
        },
        {
          "name": "서울남부"
        }
      ]
    ],
    "type": "bus",
    "extra": {
      "seatsAmount": [
        40
      ],
      "busClass": [
        "일반"
      ]
    },
    "routeId": "101052000406",
    "pattern": {
      "type": "irregular",
      "fixedDays": [
        4,
        5,
        6,
        7
      ],
      "irregularDays": [
        1,
        2,
        3
      ]
    }
  },
  {
    "departureTerminalId": "1807",
    "arrivalTerminalId": "0004",
    "durationInMinutes": [
      0
    ],
    "operator": [
      "대원고속"
    ],
    "departureTime": {
      "hour": 14,
      "minute": 40
    },
    "isTemporaryRoute": false,
    "fare": {
      "어른": [
        7500
      ],
      "초등생": [
        3800
      ],
      "중고생": [
        5300
      ]
    },
    "stops": [
      [
        {
          "name": "안중"
        },
        {
          "name": "안중오거리"
        },
        {
          "name": "숙성리"
        },
        {
          "name": "태평아파트"
        },
        {
          "name": "평택"
        },
        {
          "name": "평택대"
        },
        {
          "name": "용이동"
        },
        {
          "name": "서울남부"
        }
      ]
    ],
    "type": "bus",
    "extra": {
      "seatsAmount": [
        40
      ],
      "busClass": [
        "일반"
      ]
    },
    "routeId": "101052000406",
    "pattern": {
      "type": "irregular",
      "fixedDays": [
        4,
        5,
        6,
        7
      ],
      "irregularDays": [
        1,
        2,
        3
      ]
    }
  },
  {
    "departureTerminalId": "1807",
    "arrivalTerminalId": "0004",
    "durationInMinutes": [
      0
    ],
    "operator": [
      "대원고속"
    ],
    "departureTime": {
      "hour": 15,
      "minute": 40
    },
    "isTemporaryRoute": false,
    "fare": {
      "어른": [
        7500
      ],
      "초등생": [
        3800
      ],
      "중고생": [
        5300
      ]
    },
    "stops": [
      [
        {
          "name": "안중"
        },
        {
          "name": "안중오거리"
        },
        {
          "name": "숙성리"
        },
        {
          "name": "태평아파트"
        },
        {
          "name": "평택"
        },
        {
          "name": "평택대"
        },
        {
          "name": "용이동"
        },
        {
          "name": "서울남부"
        }
      ]
    ],
    "type": "bus",
    "extra": {
      "seatsAmount": [
        40
      ],
      "busClass": [
        "일반"
      ]
    },
    "routeId": "101052000406",
    "pattern": {
      "type": "irregular",
      "fixedDays": [
        4,
        5,
        6,
        7
      ],
      "irregularDays": [
        1,
        2,
        3
      ]
    }
  },
  {
    "departureTerminalId": "1807",
    "arrivalTerminalId": "0004",
    "durationInMinutes": [
      0
    ],
    "operator": [
      "대원고속"
    ],
    "departureTime": {
      "hour": 16,
      "minute": 30
    },
    "isTemporaryRoute": false,
    "fare": {
      "어른": [
        7500
      ],
      "초등생": [
        3800
      ],
      "중고생": [
        5300
      ]
    },
    "stops": [
      [
        {
          "name": "안중"
        },
        {
          "name": "안중오거리"
        },
        {
          "name": "숙성리"
        },
        {
          "name": "태평아파트"
        },
        {
          "name": "평택"
        },
        {
          "name": "평택대"
        },
        {
          "name": "용이동"
        },
        {
          "name": "서울남부"
        }
      ]
    ],
    "type": "bus",
    "extra": {
      "seatsAmount": [
        40
      ],
      "busClass": [
        "일반"
      ]
    },
    "routeId": "101052000406",
    "pattern": {
      "type": "irregular",
      "fixedDays": [
        4,
        5,
        6,
        7
      ],
      "irregularDays": [
        1,
        2,
        3
      ]
    }
  },
  {
    "departureTerminalId": "1807",
    "arrivalTerminalId": "0004",
    "durationInMinutes": [
      0
    ],
    "operator": [
      "대원고속"
    ],
    "departureTime": {
      "hour": 17,
      "minute": 30
    },
    "isTemporaryRoute": false,
    "fare": {
      "어른": [
        7500
      ],
      "초등생": [
        3800
      ],
      "중고생": [
        5300
      ]
    },
    "stops": [
      [
        {
          "name": "안중"
        },
        {
          "name": "안중오거리"
        },
        {
          "name": "숙성리"
        },
        {
          "name": "태평아파트"
        },
        {
          "name": "평택"
        },
        {
          "name": "평택대"
        },
        {
          "name": "용이동"
        },
        {
          "name": "서울남부"
        }
      ]
    ],
    "type": "bus",
    "extra": {
      "seatsAmount": [
        40
      ],
      "busClass": [
        "일반"
      ]
    },
    "routeId": "101052000406",
    "pattern": {
      "type": "irregular",
      "fixedDays": [
        4,
        5,
        6,
        7
      ],
      "irregularDays": [
        1,
        2,
        3
      ]
    }
  },
  {
    "departureTerminalId": "1807",
    "arrivalTerminalId": "0004",
    "durationInMinutes": [
      0
    ],
    "operator": [
      "대원고속"
    ],
    "departureTime": {
      "hour": 18,
      "minute": 0
    },
    "isTemporaryRoute": false,
    "fare": {
      "어른": [
        7500
      ],
      "초등생": [
        3800
      ],
      "중고생": [
        5300
      ]
    },
    "stops": [
      [
        {
          "name": "안중"
        },
        {
          "name": "안중오거리"
        },
        {
          "name": "숙성리"
        },
        {
          "name": "태평아파트"
        },
        {
          "name": "평택"
        },
        {
          "name": "평택대"
        },
        {
          "name": "용이동"
        },
        {
          "name": "서울남부"
        }
      ]
    ],
    "type": "bus",
    "extra": {
      "seatsAmount": [
        40
      ],
      "busClass": [
        "일반"
      ]
    },
    "routeId": "101052000406",
    "pattern": {
      "type": "irregular",
      "fixedDays": [
        4,
        5,
        6,
        7
      ],
      "irregularDays": [
        1,
        2,
        3
      ]
    }
  },
  {
    "departureTerminalId": "1807",
    "arrivalTerminalId": "0004",
    "durationInMinutes": [
      0
    ],
    "operator": [
      "대원고속"
    ],
    "departureTime": {
      "hour": 19,
      "minute": 30
    },
    "isTemporaryRoute": false,
    "fare": {
      "어른": [
        7500
      ],
      "초등생": [
        3800
      ],
      "중고생": [
        5300
      ]
    },
    "stops": [
      [
        {
          "name": "안중"
        },
        {
          "name": "안중오거리"
        },
        {
          "name": "숙성리"
        },
        {
          "name": "태평아파트"
        },
        {
          "name": "평택"
        },
        {
          "name": "평택대"
        },
        {
          "name": "용이동"
        },
        {
          "name": "서울남부"
        }
      ]
    ],
    "type": "bus",
    "extra": {
      "seatsAmount": [
        40
      ],
      "busClass": [
        "일반"
      ]
    },
    "routeId": "101052000406",
    "pattern": {
      "type": "irregular",
      "fixedDays": [
        4,
        5,
        6,
        7
      ],
      "irregularDays": [
        1,
        2,
        3
      ]
    }
  },
  {
    "departureTerminalId": "1807",
    "arrivalTerminalId": "0004",
    "durationInMinutes": [
      0
    ],
    "operator": [
      "대원고속"
    ],
    "departureTime": {
      "hour": 20,
      "minute": 20
    },
    "isTemporaryRoute": false,
    "fare": {
      "어른": [
        7500
      ],
      "초등생": [
        3800
      ],
      "중고생": [
        5300
      ]
    },
    "stops": [
      [
        {
          "name": "안중"
        },
        {
          "name": "안중오거리"
        },
        {
          "name": "숙성리"
        },
        {
          "name": "태평아파트"
        },
        {
          "name": "평택"
        },
        {
          "name": "평택대"
        },
        {
          "name": "용이동"
        },
        {
          "name": "서울남부"
        }
      ]
    ],
    "type": "bus",
    "extra": {
      "seatsAmount": [
        40
      ],
      "busClass": [
        "일반"
      ]
    },
    "routeId": "101052000406",
    "pattern": {
      "type": "irregular",
      "fixedDays": [
        4,
        5,
        6,
        7
      ],
      "irregularDays": [
        1,
        2,
        3
      ]
    }
  }
]