[
  {
    "departureTerminalId": "1957",
    "arrivalTerminalId": "9337",
    "durationInMinutes": [
      0
    ],
    "operator": [
      "(주)경기고속"
    ],
    "busClass": [
      "심야우등1"
    ],
    "departureTime": {
      "hour": 2,
      "minute": 5
    },
    "isTemporaryRoute": false,
    "seatsAmount": [
      28
    ],
    "fare": {
      "어른": [
        21100
      ],
      "초등생": [
        10600
      ],
      "중고생": [
        14800
      ]
    },
    "pattern": {
      "type": "everyday"
    }
  },
  {
    "departureTerminalId": "1957",
    "arrivalTerminalId": "9337",
    "durationInMinutes": [
      0
    ],
    "operator": [
      "(주)경기고속"
    ],
    "busClass": [
      "시외우등"
    ],
    "departureTime": {
      "hour": 4,
      "minute": 35
    },
    "isTemporaryRoute": false,
    "seatsAmount": [
      28
    ],
    "fare": {
      "어른": [
        17600
      ],
      "초등생": [
        8800
      ],
      "중고생": [
        12300
      ]
    },
    "pattern": {
      "type": "everyday"
    }
  },
  {
    "departureTerminalId": "1957",
    "arrivalTerminalId": "9337",
    "durationInMinutes": [
      0
    ],
    "operator": [
      "(주)경기고속"
    ],
    "busClass": [
      "시외우등"
    ],
    "departureTime": {
      "hour": 7,
      "minute": 5
    },
    "isTemporaryRoute": false,
    "seatsAmount": [
      28
    ],
    "fare": {
      "어른": [
        17600
      ],
      "초등생": [
        8800
      ],
      "중고생": [
        12300
      ]
    },
    "pattern": {
      "type": "everyday"
    }
  },
  {
    "departureTerminalId": "1957",
    "arrivalTerminalId": "9337",
    "durationInMinutes": [
      0
    ],
    "operator": [
      "(주)경기고속"
    ],
    "busClass": [
      "시외우등"
    ],
    "departureTime": {
      "hour": 12,
      "minute": 35
    },
    "isTemporaryRoute": false,
    "seatsAmount": [
      28
    ],
    "fare": {
      "어른": [
        17600
      ],
      "초등생": [
        8800
      ],
      "중고생": [
        12300
      ]
    },
    "pattern": {
      "type": "everyday"
    }
  },
  {
    "departureTerminalId": "1957",
    "arrivalTerminalId": "9337",
    "durationInMinutes": [
      0
    ],
    "operator": [
      "(주)경기고속"
    ],
    "busClass": [
      "시외우등"
    ],
    "departureTime": {
      "hour": 15,
      "minute": 5
    },
    "isTemporaryRoute": false,
    "seatsAmount": [
      28
    ],
    "fare": {
      "어른": [
        17600
      ],
      "초등생": [
        8800
      ],
      "중고생": [
        12300
      ]
    },
    "pattern": {
      "type": "everyday"
    }
  },
  {
    "departureTerminalId": "1957",
    "arrivalTerminalId": "9337",
    "durationInMinutes": [
      0
    ],
    "operator": [
      "(주)경기고속"
    ],
    "busClass": [
      "시외우등"
    ],
    "departureTime": {
      "hour": 21,
      "minute": 35
    },
    "isTemporaryRoute": false,
    "seatsAmount": [
      28
    ],
    "fare": {
      "어른": [
        17600
      ],
      "초등생": [
        8800
      ],
      "중고생": [
        12300
      ]
    },
    "pattern": {
      "type": "everyday"
    }
  }
]