[
  {
    "departureTerminalId": "4017",
    "arrivalTerminalId": "4040",
    "durationInMinutes": [
      0
    ],
    "operator": [
      "㈜충남고속"
    ],
    "departureTime": {
      "hour": 9,
      "minute": 48
    },
    "isTemporaryRoute": false,
    "fare": {
      "어른": [
        5600
      ],
      "초등생": [
        2800
      ],
      "중고생": [
        4500
      ]
    },
    "stops": [
      [
        {
          "name": "유구"
        },
        {
          "name": "신양"
        },
        {
          "name": "임성동"
        },
        {
          "name": "예산"
        },
        {
          "name": "삽교천"
        },
        {
          "name": "덕산(진천)"
        },
        {
          "name": "홍성(내포시)"
        },
        {
          "name": "충의사"
        },
        {
          "name": "광천리"
        },
        {
          "name": "한서대"
        },
        {
          "name": "해미"
        },
        {
          "name": "서산"
        }
      ]
    ],
    "type": "bus",
    "extra": {
      "seatsAmount": [
        0
      ],
      "busClass": [
        "일반"
      ]
    },
    "routeId": "404017401004",
    "pattern": {
      "type": "unknown"
    }
  }
]