[
  {
    "departureTerminalId": "4017",
    "arrivalTerminalId": "4498",
    "durationInMinutes": [
      0
    ],
    "operator": [
      "공통"
    ],
    "busClass": [
      "일반"
    ],
    "departureTime": {
      "hour": 8,
      "minute": 50
    },
    "isTemporaryRoute": false,
    "seatsAmount": [
      0
    ],
    "fare": {
      "어른": [
        0
      ],
      "초등생": [
        0
      ],
      "중고생": [
        0
      ]
    },
    "stops": [
      [
        {
          "name": "유구"
        },
        {
          "name": "배방"
        },
        {
          "name": "봉강교(서부휴게소)"
        }
      ]
    ],
    "pattern": {
      "type": "unknown"
    }
  }
]