[
  {
    "departureTerminalId": "7018",
    "arrivalTerminalId": "7021",
    "durationInMinutes": [
      0
    ],
    "operator": [
      "공통"
    ],
    "departureTime": {
      "hour": 10,
      "minute": 30
    },
    "isTemporaryRoute": false,
    "fare": {
      "어른": [
        2300
      ],
      "초등생": [
        1200
      ],
      "중고생": [
        1800
      ]
    },
    "stops": [
      [
        {
          "name": "부안"
        },
        {
          "name": "신태인"
        },
        {
          "name": "광주(유ㆍ스퀘어)"
        }
      ]
    ],
    "type": "bus",
    "extra": {
      "seatsAmount": [
        0
      ],
      "busClass": [
        "일반"
      ]
    },
    "routeId": "707018940102",
    "pattern": {
      "type": "irregular",
      "fixedDays": [
        1,
        2,
        3,
        7
      ],
      "irregularDays": [
        4,
        5,
        6
      ]
    }
  },
  {
    "departureTerminalId": "7018",
    "arrivalTerminalId": "7021",
    "durationInMinutes": [
      0
    ],
    "operator": [
      "공통"
    ],
    "departureTime": {
      "hour": 14,
      "minute": 40
    },
    "isTemporaryRoute": false,
    "fare": {
      "어른": [
        2300
      ],
      "초등생": [
        1200
      ],
      "중고생": [
        1800
      ]
    },
    "stops": [
      [
        {
          "name": "부안"
        },
        {
          "name": "신태인"
        },
        {
          "name": "광주(유ㆍ스퀘어)"
        }
      ]
    ],
    "type": "bus",
    "extra": {
      "seatsAmount": [
        0
      ],
      "busClass": [
        "일반"
      ]
    },
    "routeId": "707018940102",
    "pattern": {
      "type": "irregular",
      "fixedDays": [
        1,
        2,
        3,
        7
      ],
      "irregularDays": [
        4,
        5,
        6
      ]
    }
  },
  {
    "departureTerminalId": "7018",
    "arrivalTerminalId": "7021",
    "durationInMinutes": [
      0
    ],
    "operator": [
      "공통"
    ],
    "departureTime": {
      "hour": 18,
      "minute": 20
    },
    "isTemporaryRoute": false,
    "fare": {
      "어른": [
        2300
      ],
      "초등생": [
        1200
      ],
      "중고생": [
        1800
      ]
    },
    "stops": [
      [
        {
          "name": "부안"
        },
        {
          "name": "신태인"
        },
        {
          "name": "광주(유ㆍ스퀘어)"
        }
      ]
    ],
    "type": "bus",
    "extra": {
      "seatsAmount": [
        0
      ],
      "busClass": [
        "일반"
      ]
    },
    "routeId": "707018940102",
    "pattern": {
      "type": "irregular",
      "fixedDays": [
        1,
        2,
        3,
        7
      ],
      "irregularDays": [
        4,
        5,
        6
      ]
    }
  }
]