[
  {
    "departureTerminalId": "7429",
    "arrivalTerminalId": "7084",
    "durationInMinutes": [
      0
    ],
    "operator": [
      "㈜광신고속"
    ],
    "busClass": [
      "일반"
    ],
    "departureTime": {
      "hour": 15,
      "minute": 0
    },
    "isTemporaryRoute": false,
    "seatsAmount": [
      41
    ],
    "fare": {
      "어른": [
        1800
      ],
      "초등생": [
        900
      ],
      "중고생": [
        1400
      ]
    },
    "stops": [
      [
        {
          "name": "내장사"
        },
        {
          "name": "정읍"
        },
        {
          "name": "운암동"
        },
        {
          "name": "광주(유ㆍ스퀘어)"
        }
      ]
    ],
    "pattern": {
      "type": "everyday"
    }
  }
]