[
  {
    "departureTerminalId": "8031",
    "arrivalTerminalId": "8070",
    "durationInMinutes": [
      0
    ],
    "operator": [
      "㈜광우고속"
    ],
    "departureTime": {
      "hour": 6,
      "minute": 40
    },
    "isTemporaryRoute": false,
    "fare": {
      "어른": [
        9400
      ],
      "초등생": [
        4700
      ],
      "중고생": [
        7500
      ]
    },
    "stops": [
      [
        {
          "name": "보성"
        },
        {
          "name": "보성북문"
        },
        {
          "name": "복내"
        },
        {
          "name": "문덕"
        },
        {
          "name": "화순"
        },
        {
          "name": "소태"
        },
        {
          "name": "학동"
        },
        {
          "name": "광주(유ㆍ스퀘어)"
        }
      ]
    ],
    "type": "bus",
    "extra": {
      "seatsAmount": [
        0
      ],
      "busClass": [
        "일반"
      ]
    },
    "routeId": "808031940107",
    "pattern": {
      "type": "unknown"
    }
  },
  {
    "departureTerminalId": "8031",
    "arrivalTerminalId": "8070",
    "durationInMinutes": [
      0
    ],
    "operator": [
      "㈜광우고속"
    ],
    "departureTime": {
      "hour": 7,
      "minute": 40
    },
    "isTemporaryRoute": false,
    "fare": {
      "어른": [
        9400
      ],
      "초등생": [
        4700
      ],
      "중고생": [
        7500
      ]
    },
    "stops": [
      [
        {
          "name": "보성"
        },
        {
          "name": "보성북문"
        },
        {
          "name": "복내"
        },
        {
          "name": "문덕"
        },
        {
          "name": "화순"
        },
        {
          "name": "소태"
        },
        {
          "name": "학동"
        },
        {
          "name": "광주(유ㆍ스퀘어)"
        }
      ]
    ],
    "type": "bus",
    "extra": {
      "seatsAmount": [
        0
      ],
      "busClass": [
        "일반"
      ]
    },
    "routeId": "808031940107",
    "pattern": {
      "type": "unknown"
    }
  },
  {
    "departureTerminalId": "8031",
    "arrivalTerminalId": "8070",
    "durationInMinutes": [
      0
    ],
    "operator": [
      "㈜광우고속"
    ],
    "departureTime": {
      "hour": 8,
      "minute": 20
    },
    "isTemporaryRoute": false,
    "fare": {
      "어른": [
        10200
      ],
      "초등생": [
        5100
      ],
      "중고생": [
        8200
      ]
    },
    "stops": [
      [
        {
          "name": "보성"
        },
        {
          "name": "보성북문"
        },
        {
          "name": "소태"
        },
        {
          "name": "학동"
        },
        {
          "name": "광주(유ㆍ스퀘어)"
        }
      ]
    ],
    "type": "bus",
    "extra": {
      "seatsAmount": [
        28
      ],
      "busClass": [
        "시외우등"
      ]
    },
    "routeId": "808031940109",
    "pattern": {
      "type": "unknown"
    }
  },
  {
    "departureTerminalId": "8031",
    "arrivalTerminalId": "8070",
    "durationInMinutes": [
      0
    ],
    "operator": [
      "㈜광우고속"
    ],
    "departureTime": {
      "hour": 9,
      "minute": 10
    },
    "isTemporaryRoute": false,
    "fare": {
      "어른": [
        9400
      ],
      "초등생": [
        4700
      ],
      "중고생": [
        7500
      ]
    },
    "stops": [
      [
        {
          "name": "보성"
        },
        {
          "name": "보성북문"
        },
        {
          "name": "복내"
        },
        {
          "name": "문덕"
        },
        {
          "name": "화순"
        },
        {
          "name": "소태"
        },
        {
          "name": "학동"
        },
        {
          "name": "광주(유ㆍ스퀘어)"
        }
      ]
    ],
    "type": "bus",
    "extra": {
      "seatsAmount": [
        0
      ],
      "busClass": [
        "일반"
      ]
    },
    "routeId": "808031940107",
    "pattern": {
      "type": "unknown"
    }
  },
  {
    "departureTerminalId": "8031",
    "arrivalTerminalId": "8070",
    "durationInMinutes": [
      0
    ],
    "operator": [
      "㈜광우고속"
    ],
    "departureTime": {
      "hour": 10,
      "minute": 40
    },
    "isTemporaryRoute": false,
    "fare": {
      "어른": [
        10200
      ],
      "초등생": [
        5100
      ],
      "중고생": [
        8200
      ]
    },
    "stops": [
      [
        {
          "name": "율포"
        },
        {
          "name": "녹차밭"
        },
        {
          "name": "보성"
        },
        {
          "name": "보성북문"
        },
        {
          "name": "소태"
        },
        {
          "name": "학동"
        },
        {
          "name": "광주(유ㆍ스퀘어)"
        }
      ]
    ],
    "type": "bus",
    "extra": {
      "seatsAmount": [
        28
      ],
      "busClass": [
        "시외우등"
      ]
    },
    "routeId": "808081940101",
    "pattern": {
      "type": "unknown"
    }
  },
  {
    "departureTerminalId": "8031",
    "arrivalTerminalId": "8070",
    "durationInMinutes": [
      0
    ],
    "operator": [
      "㈜광우고속"
    ],
    "departureTime": {
      "hour": 11,
      "minute": 40
    },
    "isTemporaryRoute": false,
    "fare": {
      "어른": [
        9400
      ],
      "초등생": [
        4700
      ],
      "중고생": [
        7500
      ]
    },
    "stops": [
      [
        {
          "name": "보성"
        },
        {
          "name": "보성북문"
        },
        {
          "name": "복내"
        },
        {
          "name": "화순"
        },
        {
          "name": "소태"
        },
        {
          "name": "학동"
        },
        {
          "name": "광주(유ㆍ스퀘어)"
        }
      ]
    ],
    "type": "bus",
    "extra": {
      "seatsAmount": [
        0
      ],
      "busClass": [
        "일반"
      ]
    },
    "routeId": "808031940110",
    "pattern": {
      "type": "unknown"
    }
  },
  {
    "departureTerminalId": "8031",
    "arrivalTerminalId": "8070",
    "durationInMinutes": [
      0
    ],
    "operator": [
      "㈜광우고속"
    ],
    "departureTime": {
      "hour": 12,
      "minute": 40
    },
    "isTemporaryRoute": false,
    "fare": {
      "어른": [
        10200
      ],
      "초등생": [
        5100
      ],
      "중고생": [
        8200
      ]
    },
    "stops": [
      [
        {
          "name": "율포"
        },
        {
          "name": "녹차밭"
        },
        {
          "name": "보성"
        },
        {
          "name": "보성북문"
        },
        {
          "name": "소태"
        },
        {
          "name": "학동"
        },
        {
          "name": "광주(유ㆍ스퀘어)"
        }
      ]
    ],
    "type": "bus",
    "extra": {
      "seatsAmount": [
        28
      ],
      "busClass": [
        "시외우등"
      ]
    },
    "routeId": "808081940101",
    "pattern": {
      "type": "unknown"
    }
  },
  {
    "departureTerminalId": "8031",
    "arrivalTerminalId": "8070",
    "durationInMinutes": [
      0
    ],
    "operator": [
      "㈜광우고속"
    ],
    "departureTime": {
      "hour": 13,
      "minute": 40
    },
    "isTemporaryRoute": false,
    "fare": {
      "어른": [
        9400
      ],
      "초등생": [
        4700
      ],
      "중고생": [
        7500
      ]
    },
    "stops": [
      [
        {
          "name": "보성"
        },
        {
          "name": "보성북문"
        },
        {
          "name": "복내"
        },
        {
          "name": "문덕"
        },
        {
          "name": "화순"
        },
        {
          "name": "소태"
        },
        {
          "name": "학동"
        },
        {
          "name": "광주(유ㆍ스퀘어)"
        }
      ]
    ],
    "type": "bus",
    "extra": {
      "seatsAmount": [
        0
      ],
      "busClass": [
        "일반"
      ]
    },
    "routeId": "808031940107",
    "pattern": {
      "type": "unknown"
    }
  },
  {
    "departureTerminalId": "8031",
    "arrivalTerminalId": "8070",
    "durationInMinutes": [
      0
    ],
    "operator": [
      "㈜광우고속"
    ],
    "departureTime": {
      "hour": 14,
      "minute": 40
    },
    "isTemporaryRoute": false,
    "fare": {
      "어른": [
        10200
      ],
      "초등생": [
        5100
      ],
      "중고생": [
        8200
      ]
    },
    "stops": [
      [
        {
          "name": "율포"
        },
        {
          "name": "녹차밭"
        },
        {
          "name": "보성"
        },
        {
          "name": "보성북문"
        },
        {
          "name": "소태"
        },
        {
          "name": "학동"
        },
        {
          "name": "광주(유ㆍ스퀘어)"
        }
      ]
    ],
    "type": "bus",
    "extra": {
      "seatsAmount": [
        28
      ],
      "busClass": [
        "시외우등"
      ]
    },
    "routeId": "808081940101",
    "pattern": {
      "type": "unknown"
    }
  },
  {
    "departureTerminalId": "8031",
    "arrivalTerminalId": "8070",
    "durationInMinutes": [
      0
    ],
    "operator": [
      "㈜광우고속"
    ],
    "departureTime": {
      "hour": 15,
      "minute": 40
    },
    "isTemporaryRoute": false,
    "fare": {
      "어른": [
        9400
      ],
      "초등생": [
        4700
      ],
      "중고생": [
        7500
      ]
    },
    "stops": [
      [
        {
          "name": "보성"
        },
        {
          "name": "보성북문"
        },
        {
          "name": "복내"
        },
        {
          "name": "화순"
        },
        {
          "name": "소태"
        },
        {
          "name": "학동"
        },
        {
          "name": "광주(유ㆍ스퀘어)"
        }
      ]
    ],
    "type": "bus",
    "extra": {
      "seatsAmount": [
        0
      ],
      "busClass": [
        "일반"
      ]
    },
    "routeId": "808031940110",
    "pattern": {
      "type": "unknown"
    }
  },
  {
    "departureTerminalId": "8031",
    "arrivalTerminalId": "8070",
    "durationInMinutes": [
      0
    ],
    "operator": [
      "㈜광우고속"
    ],
    "departureTime": {
      "hour": 16,
      "minute": 40
    },
    "isTemporaryRoute": false,
    "fare": {
      "어른": [
        10200
      ],
      "초등생": [
        5100
      ],
      "중고생": [
        8200
      ]
    },
    "stops": [
      [
        {
          "name": "율포"
        },
        {
          "name": "제암산휴양림"
        },
        {
          "name": "보성"
        },
        {
          "name": "보성북문"
        },
        {
          "name": "소태"
        },
        {
          "name": "학동"
        },
        {
          "name": "광주(유ㆍ스퀘어)"
        }
      ]
    ],
    "type": "bus",
    "extra": {
      "seatsAmount": [
        28
      ],
      "busClass": [
        "시외우등"
      ]
    },
    "routeId": "808081940106",
    "pattern": {
      "type": "unknown"
    }
  },
  {
    "departureTerminalId": "8031",
    "arrivalTerminalId": "8070",
    "durationInMinutes": [
      0
    ],
    "operator": [
      "㈜광우고속"
    ],
    "departureTime": {
      "hour": 17,
      "minute": 45
    },
    "isTemporaryRoute": false,
    "fare": {
      "어른": [
        9400
      ],
      "초등생": [
        4700
      ],
      "중고생": [
        7500
      ]
    },
    "stops": [
      [
        {
          "name": "보성"
        },
        {
          "name": "보성북문"
        },
        {
          "name": "복내"
        },
        {
          "name": "문덕"
        },
        {
          "name": "화순"
        },
        {
          "name": "소태"
        },
        {
          "name": "학동"
        },
        {
          "name": "광주(유ㆍ스퀘어)"
        }
      ]
    ],
    "type": "bus",
    "extra": {
      "seatsAmount": [
        0
      ],
      "busClass": [
        "일반"
      ]
    },
    "routeId": "808031940107",
    "pattern": {
      "type": "unknown"
    }
  },
  {
    "departureTerminalId": "8031",
    "arrivalTerminalId": "8070",
    "durationInMinutes": [
      0
    ],
    "operator": [
      "㈜광우고속"
    ],
    "departureTime": {
      "hour": 18,
      "minute": 30
    },
    "isTemporaryRoute": false,
    "fare": {
      "어른": [
        10200
      ],
      "초등생": [
        5100
      ],
      "중고생": [
        8200
      ]
    },
    "stops": [
      [
        {
          "name": "율포"
        },
        {
          "name": "녹차밭"
        },
        {
          "name": "보성"
        },
        {
          "name": "보성북문"
        },
        {
          "name": "소태"
        },
        {
          "name": "학동"
        },
        {
          "name": "광주(유ㆍ스퀘어)"
        }
      ]
    ],
    "type": "bus",
    "extra": {
      "seatsAmount": [
        28
      ],
      "busClass": [
        "시외우등"
      ]
    },
    "routeId": "808081940101",
    "pattern": {
      "type": "unknown"
    }
  },
  {
    "departureTerminalId": "8031",
    "arrivalTerminalId": "8070",
    "durationInMinutes": [
      0
    ],
    "operator": [
      "㈜광우고속"
    ],
    "departureTime": {
      "hour": 19,
      "minute": 15
    },
    "isTemporaryRoute": false,
    "fare": {
      "어른": [
        9400
      ],
      "초등생": [
        4700
      ],
      "중고생": [
        7500
      ]
    },
    "stops": [
      [
        {
          "name": "보성"
        },
        {
          "name": "보성북문"
        },
        {
          "name": "복내"
        },
        {
          "name": "화순"
        },
        {
          "name": "소태"
        },
        {
          "name": "학동"
        },
        {
          "name": "광주(유ㆍ스퀘어)"
        }
      ]
    ],
    "type": "bus",
    "extra": {
      "seatsAmount": [
        0
      ],
      "busClass": [
        "일반"
      ]
    },
    "routeId": "808031940110",
    "pattern": {
      "type": "unknown"
    }
  },
  {
    "departureTerminalId": "8031",
    "arrivalTerminalId": "8070",
    "durationInMinutes": [
      0
    ],
    "operator": [
      "㈜광우고속"
    ],
    "departureTime": {
      "hour": 19,
      "minute": 50
    },
    "isTemporaryRoute": false,
    "fare": {
      "어른": [
        10200
      ],
      "초등생": [
        5100
      ],
      "중고생": [
        8200
      ]
    },
    "stops": [
      [
        {
          "name": "보성"
        },
        {
          "name": "보성북문"
        },
        {
          "name": "소태"
        },
        {
          "name": "학동"
        },
        {
          "name": "광주(유ㆍ스퀘어)"
        }
      ]
    ],
    "type": "bus",
    "extra": {
      "seatsAmount": [
        28
      ],
      "busClass": [
        "시외우등"
      ]
    },
    "routeId": "808031940109",
    "pattern": {
      "type": "unknown"
    }
  },
  {
    "departureTerminalId": "8031",
    "arrivalTerminalId": "8070",
    "durationInMinutes": [
      0
    ],
    "operator": [
      "㈜광우고속"
    ],
    "departureTime": {
      "hour": 20,
      "minute": 30
    },
    "isTemporaryRoute": false,
    "fare": {
      "어른": [
        9400
      ],
      "초등생": [
        4700
      ],
      "중고생": [
        7500
      ]
    },
    "stops": [
      [
        {
          "name": "보성"
        },
        {
          "name": "보성북문"
        },
        {
          "name": "복내"
        },
        {
          "name": "화순"
        },
        {
          "name": "소태"
        },
        {
          "name": "학동"
        },
        {
          "name": "광주(유ㆍ스퀘어)"
        }
      ]
    ],
    "type": "bus",
    "extra": {
      "seatsAmount": [
        0
      ],
      "busClass": [
        "일반"
      ]
    },
    "routeId": "808031940110",
    "pattern": {
      "type": "unknown"
    }
  }
]