[
  {
    "departureTerminalId": "8042",
    "arrivalTerminalId": "8007",
    "durationInMinutes": [
      0
    ],
    "operator": [
      "㈜전북고속"
    ],
    "departureTime": {
      "hour": 16,
      "minute": 0
    },
    "isTemporaryRoute": false,
    "fare": {
      "어른": [
        9100
      ],
      "초등생": [
        4600
      ],
      "중고생": [
        7300
      ]
    },
    "stops": [
      [
        {
          "name": "여천"
        },
        {
          "name": "순천"
        },
        {
          "name": "순천북부"
        },
        {
          "name": "구례"
        },
        {
          "name": "남원"
        }
      ]
    ],
    "type": "bus",
    "extra": {
      "seatsAmount": [
        45
      ],
      "busClass": [
        "일반"
      ]
    },
    "routeId": "808042701001",
    "pattern": {
      "type": "specific-day",
      "days": [
        1,
        2,
        3,
        4,
        5,
        6,
        7
      ]
    }
  }
]