[
  {
    "departureTerminalId": "8050",
    "arrivalTerminalId": "8010",
    "durationInMinutes": [
      0
    ],
    "operator": [
      "금호고속(주)"
    ],
    "departureTime": {
      "hour": 8,
      "minute": 50
    },
    "isTemporaryRoute": false,
    "fare": {
      "어른": [
        2900
      ],
      "초등생": [
        1500
      ],
      "중고생": [
        2300
      ]
    },
    "stops": [
      [
        {
          "name": "완도"
        },
        {
          "name": "원동"
        },
        {
          "name": "남창"
        },
        {
          "name": "월송"
        },
        {
          "name": "해남"
        },
        {
          "name": "독천"
        },
        {
          "name": "삼호"
        },
        {
          "name": "남악"
        },
        {
          "name": "목포"
        }
      ]
    ],
    "type": "bus",
    "extra": {
      "seatsAmount": [
        45
      ],
      "busClass": [
        "일반"
      ]
    },
    "routeId": "808050802406",
    "pattern": {
      "type": "everyday"
    }
  },
  {
    "departureTerminalId": "8050",
    "arrivalTerminalId": "8010",
    "durationInMinutes": [
      0
    ],
    "operator": [
      "금호고속(주)"
    ],
    "departureTime": {
      "hour": 13,
      "minute": 50
    },
    "isTemporaryRoute": false,
    "fare": {
      "어른": [
        2900
      ],
      "초등생": [
        1500
      ],
      "중고생": [
        2300
      ]
    },
    "stops": [
      [
        {
          "name": "완도"
        },
        {
          "name": "원동"
        },
        {
          "name": "남창"
        },
        {
          "name": "월송"
        },
        {
          "name": "해남"
        },
        {
          "name": "강진"
        },
        {
          "name": "장흥"
        },
        {
          "name": "배산"
        },
        {
          "name": "보성"
        },
        {
          "name": "예당"
        },
        {
          "name": "조성"
        },
        {
          "name": "벌교"
        },
        {
          "name": "순천"
        },
        {
          "name": "광양"
        },
        {
          "name": "동광양(중마)"
        },
        {
          "name": "부산서부"
        }
      ]
    ],
    "type": "bus",
    "extra": {
      "seatsAmount": [
        40
      ],
      "busClass": [
        "일반"
      ]
    },
    "routeId": "808050900209",
    "pattern": {
      "type": "everyday"
    }
  },
  {
    "departureTerminalId": "8050",
    "arrivalTerminalId": "8010",
    "durationInMinutes": [
      0
    ],
    "operator": [
      "금호고속(주)"
    ],
    "departureTime": {
      "hour": 15,
      "minute": 10
    },
    "isTemporaryRoute": false,
    "fare": {
      "어른": [
        2900
      ],
      "초등생": [
        1500
      ],
      "중고생": [
        2300
      ]
    },
    "stops": [
      [
        {
          "name": "완도"
        },
        {
          "name": "원동"
        },
        {
          "name": "남창"
        },
        {
          "name": "월송"
        },
        {
          "name": "해남"
        },
        {
          "name": "독천"
        },
        {
          "name": "삼호"
        },
        {
          "name": "남악"
        },
        {
          "name": "목포"
        }
      ]
    ],
    "type": "bus",
    "extra": {
      "seatsAmount": [
        45
      ],
      "busClass": [
        "일반"
      ]
    },
    "routeId": "808050802406",
    "pattern": {
      "type": "everyday"
    }
  },
  {
    "departureTerminalId": "8050",
    "arrivalTerminalId": "8010",
    "durationInMinutes": [
      0
    ],
    "operator": [
      "금호고속(주)"
    ],
    "departureTime": {
      "hour": 15,
      "minute": 40
    },
    "isTemporaryRoute": false,
    "fare": {
      "어른": [
        2900
      ],
      "초등생": [
        1500
      ],
      "중고생": [
        2300
      ]
    },
    "stops": [
      [
        {
          "name": "완도"
        },
        {
          "name": "원동"
        },
        {
          "name": "남창"
        },
        {
          "name": "월송"
        },
        {
          "name": "해남"
        },
        {
          "name": "강진"
        },
        {
          "name": "장흥"
        },
        {
          "name": "배산"
        },
        {
          "name": "보성"
        },
        {
          "name": "예당"
        },
        {
          "name": "조성"
        },
        {
          "name": "벌교"
        },
        {
          "name": "순천"
        },
        {
          "name": "광양"
        },
        {
          "name": "동광양(중마)"
        },
        {
          "name": "부산서부"
        }
      ]
    ],
    "type": "bus",
    "extra": {
      "seatsAmount": [
        40
      ],
      "busClass": [
        "일반"
      ]
    },
    "routeId": "808050900209",
    "pattern": {
      "type": "everyday"
    }
  },
  {
    "departureTerminalId": "8050",
    "arrivalTerminalId": "8010",
    "durationInMinutes": [
      0
    ],
    "operator": [
      "금호고속(주)"
    ],
    "departureTime": {
      "hour": 18,
      "minute": 30
    },
    "isTemporaryRoute": false,
    "fare": {
      "어른": [
        2900
      ],
      "초등생": [
        1500
      ],
      "중고생": [
        2300
      ]
    },
    "stops": [
      [
        {
          "name": "완도"
        },
        {
          "name": "원동"
        },
        {
          "name": "남창"
        },
        {
          "name": "월송"
        },
        {
          "name": "해남"
        },
        {
          "name": "성전"
        },
        {
          "name": "영암"
        },
        {
          "name": "신북"
        },
        {
          "name": "나주혁신도시"
        },
        {
          "name": "송정역"
        },
        {
          "name": "광주(유ㆍ스퀘어)"
        }
      ]
    ],
    "type": "bus",
    "extra": {
      "seatsAmount": [
        45
      ],
      "busClass": [
        "일반"
      ]
    },
    "routeId": "808050940103",
    "pattern": {
      "type": "everyday"
    }
  },
  {
    "departureTerminalId": "8050",
    "arrivalTerminalId": "8010",
    "durationInMinutes": [
      0
    ],
    "operator": [
      "금호고속(주)"
    ],
    "departureTime": {
      "hour": 7,
      "minute": 50
    },
    "isTemporaryRoute": false,
    "fare": {
      "어른": [
        2900
      ],
      "초등생": [
        1500
      ],
      "중고생": [
        2300
      ]
    },
    "stops": [
      [
        {
          "name": "완도"
        },
        {
          "name": "원동"
        },
        {
          "name": "남창"
        },
        {
          "name": "월송"
        },
        {
          "name": "해남"
        },
        {
          "name": "강진"
        },
        {
          "name": "장흥"
        },
        {
          "name": "배산"
        },
        {
          "name": "보성"
        },
        {
          "name": "예당"
        },
        {
          "name": "조성"
        },
        {
          "name": "벌교"
        },
        {
          "name": "순천"
        },
        {
          "name": "광양"
        },
        {
          "name": "동광양(중마)"
        },
        {
          "name": "부산서부"
        }
      ]
    ],
    "type": "bus",
    "extra": {
      "seatsAmount": [
        40
      ],
      "busClass": [
        "일반"
      ]
    },
    "routeId": "808050900209",
    "pattern": {
      "type": "specific-day",
      "days": [
        6,
        7
      ]
    }
  }
]