[
  {
    "departureTerminalId": "8063",
    "arrivalTerminalId": "8073",
    "durationInMinutes": [
      0
    ],
    "operator": [
      "금호고속(주)"
    ],
    "departureTime": {
      "hour": 23,
      "minute": 59
    },
    "isTemporaryRoute": false,
    "fare": {
      "어른": [
        5100
      ],
      "초등생": [
        2600
      ],
      "중고생": [
        4100
      ]
    },
    "stops": [
      [
        {
          "name": "해제"
        },
        {
          "name": "망운"
        },
        {
          "name": "현경"
        },
        {
          "name": "무안"
        },
        {
          "name": "청계"
        },
        {
          "name": "목포"
        }
      ]
    ],
    "type": "bus",
    "extra": {
      "seatsAmount": [
        0
      ],
      "busClass": [
        "일반"
      ]
    },
    "routeId": "808063802401",
    "pattern": {
      "type": "irregular",
      "fixedDays": [
        2,
        6,
        7
      ],
      "irregularDays": [
        1,
        3,
        4,
        5
      ]
    }
  }
]