[
  {
    "departureTerminalId": "9303",
    "arrivalTerminalId": "1168",
    "durationInMinutes": [
      0
    ],
    "operator": [
      "(주)경기고속"
    ],
    "busClass": [
      "시외우등"
    ],
    "departureTime": {
      "hour": 7,
      "minute": 55
    },
    "isTemporaryRoute": false,
    "seatsAmount": [
      28
    ],
    "fare": {
      "어른": [
        13200
      ],
      "초등생": [
        6600
      ],
      "중고생": [
        9200
      ]
    },
    "via": [
      [
        "인천공항(제2터미널)",
        "인천공항",
        "소노캄호텔(엠블호텔)",
        "킨텍스",
        "숲속길마을7단지",
        "산내마을6-8단지",
        "두레공원",
        "지산중학교",
        "한빛마을3.6단지",
        "야당역(한빛5.9단지)",
        "한길육교",
        "가람3.4.6단지",
        "금릉역",
        "금촌역",
        "월롱역",
        "문산역(파주)"
      ]
    ],
    "pattern": {
      "type": "everyday"
    }
  },
  {
    "departureTerminalId": "9303",
    "arrivalTerminalId": "1168",
    "durationInMinutes": [
      0
    ],
    "operator": [
      "(주)경기고속"
    ],
    "busClass": [
      "시외우등"
    ],
    "departureTime": {
      "hour": 9,
      "minute": 35
    },
    "isTemporaryRoute": false,
    "seatsAmount": [
      28
    ],
    "fare": {
      "어른": [
        13200
      ],
      "초등생": [
        6600
      ],
      "중고생": [
        9200
      ]
    },
    "via": [
      [
        "인천공항(제2터미널)",
        "인천공항",
        "소노캄호텔(엠블호텔)",
        "킨텍스",
        "숲속길마을7단지",
        "산내마을6-8단지",
        "두레공원",
        "지산중학교",
        "한빛마을3.6단지",
        "야당역(한빛5.9단지)",
        "한길육교",
        "가람3.4.6단지",
        "금릉역",
        "금촌역",
        "월롱역",
        "문산역(파주)"
      ]
    ],
    "pattern": {
      "type": "everyday"
    }
  },
  {
    "departureTerminalId": "9303",
    "arrivalTerminalId": "1168",
    "durationInMinutes": [
      0
    ],
    "operator": [
      "(주)경기고속"
    ],
    "busClass": [
      "시외우등"
    ],
    "departureTime": {
      "hour": 10,
      "minute": 50
    },
    "isTemporaryRoute": false,
    "seatsAmount": [
      28
    ],
    "fare": {
      "어른": [
        13200
      ],
      "초등생": [
        6600
      ],
      "중고생": [
        9200
      ]
    },
    "via": [
      [
        "인천공항(제2터미널)",
        "인천공항",
        "소노캄호텔(엠블호텔)",
        "킨텍스",
        "숲속길마을7단지",
        "산내마을6-8단지",
        "두레공원",
        "지산중학교",
        "한빛마을3.6단지",
        "야당역(한빛5.9단지)",
        "한길육교",
        "가람3.4.6단지",
        "금릉역",
        "금촌역",
        "월롱역",
        "문산역(파주)"
      ]
    ],
    "pattern": {
      "type": "everyday"
    }
  },
  {
    "departureTerminalId": "9303",
    "arrivalTerminalId": "1168",
    "durationInMinutes": [
      0
    ],
    "operator": [
      "(주)경기고속"
    ],
    "busClass": [
      "시외우등"
    ],
    "departureTime": {
      "hour": 16,
      "minute": 10
    },
    "isTemporaryRoute": false,
    "seatsAmount": [
      28
    ],
    "fare": {
      "어른": [
        13200
      ],
      "초등생": [
        6600
      ],
      "중고생": [
        9200
      ]
    },
    "via": [
      [
        "인천공항(제2터미널)",
        "인천공항",
        "소노캄호텔(엠블호텔)",
        "킨텍스",
        "숲속길마을7단지",
        "산내마을6-8단지",
        "두레공원",
        "지산중학교",
        "한빛마을3.6단지",
        "야당역(한빛5.9단지)",
        "한길육교",
        "가람3.4.6단지",
        "금릉역",
        "금촌역",
        "월롱역",
        "문산역(파주)"
      ]
    ],
    "pattern": {
      "type": "everyday"
    }
  },
  {
    "departureTerminalId": "9303",
    "arrivalTerminalId": "1168",
    "durationInMinutes": [
      0
    ],
    "operator": [
      "(주)경기고속"
    ],
    "busClass": [
      "시외우등"
    ],
    "departureTime": {
      "hour": 17,
      "minute": 25
    },
    "isTemporaryRoute": false,
    "seatsAmount": [
      28
    ],
    "fare": {
      "어른": [
        13200
      ],
      "초등생": [
        6600
      ],
      "중고생": [
        9200
      ]
    },
    "via": [
      [
        "인천공항(제2터미널)",
        "인천공항",
        "소노캄호텔(엠블호텔)",
        "킨텍스",
        "숲속길마을7단지",
        "산내마을6-8단지",
        "두레공원",
        "지산중학교",
        "한빛마을3.6단지",
        "야당역(한빛5.9단지)",
        "한길육교",
        "가람3.4.6단지",
        "금릉역",
        "금촌역",
        "월롱역",
        "문산역(파주)"
      ]
    ],
    "pattern": {
      "type": "everyday"
    }
  },
  {
    "departureTerminalId": "9303",
    "arrivalTerminalId": "1168",
    "durationInMinutes": [
      0
    ],
    "operator": [
      "(주)경기고속"
    ],
    "busClass": [
      "시외우등"
    ],
    "departureTime": {
      "hour": 18,
      "minute": 40
    },
    "isTemporaryRoute": false,
    "seatsAmount": [
      28
    ],
    "fare": {
      "어른": [
        13200
      ],
      "초등생": [
        6600
      ],
      "중고생": [
        9200
      ]
    },
    "via": [
      [
        "인천공항(제2터미널)",
        "인천공항",
        "소노캄호텔(엠블호텔)",
        "킨텍스",
        "숲속길마을7단지",
        "산내마을6-8단지",
        "두레공원",
        "지산중학교",
        "한빛마을3.6단지",
        "야당역(한빛5.9단지)",
        "한길육교",
        "가람3.4.6단지",
        "금릉역",
        "금촌역",
        "월롱역",
        "문산역(파주)"
      ]
    ],
    "pattern": {
      "type": "everyday"
    }
  }
]