[
  {
    "departureTerminalId": "9303",
    "arrivalTerminalId": "1879",
    "durationInMinutes": [
      0
    ],
    "operator": [
      "대원고속"
    ],
    "departureTime": {
      "hour": 9,
      "minute": 55
    },
    "isTemporaryRoute": false,
    "fare": {
      "어른": [
        13200
      ],
      "초등생": [
        6600
      ],
      "중고생": [
        10600
      ]
    },
    "stops": [
      [
        {
          "name": "인천공항(제2터미널)"
        },
        {
          "name": "인천공항"
        },
        {
          "name": "화성세무서"
        },
        {
          "name": "봉담국민체육센터"
        },
        {
          "name": "봉담중심상가"
        },
        {
          "name": "화성에듀시티파라곤"
        },
        {
          "name": "신일해피트리2차"
        },
        {
          "name": "융건릉사거리"
        },
        {
          "name": "우미린2차"
        },
        {
          "name": "향남터미널"
        },
        {
          "name": "안중"
        }
      ]
    ],
    "type": "bus",
    "extra": {
      "seatsAmount": [
        28
      ],
      "busClass": [
        "시외우등"
      ]
    },
    "routeId": "939337105205",
    "pattern": {
      "type": "specific-day",
      "days": [
        1,
        2,
        3,
        4,
        5,
        6,
        7
      ]
    }
  },
  {
    "departureTerminalId": "9303",
    "arrivalTerminalId": "1879",
    "durationInMinutes": [
      0
    ],
    "operator": [
      "대원고속"
    ],
    "departureTime": {
      "hour": 17,
      "minute": 10
    },
    "isTemporaryRoute": false,
    "fare": {
      "어른": [
        13200
      ],
      "초등생": [
        6600
      ],
      "중고생": [
        10600
      ]
    },
    "stops": [
      [
        {
          "name": "인천공항(제2터미널)"
        },
        {
          "name": "인천공항"
        },
        {
          "name": "화성세무서"
        },
        {
          "name": "봉담국민체육센터"
        },
        {
          "name": "봉담중심상가"
        },
        {
          "name": "화성에듀시티파라곤"
        },
        {
          "name": "신일해피트리2차"
        },
        {
          "name": "융건릉사거리"
        },
        {
          "name": "우미린2차"
        },
        {
          "name": "향남터미널"
        },
        {
          "name": "안중"
        }
      ]
    ],
    "type": "bus",
    "extra": {
      "seatsAmount": [
        28
      ],
      "busClass": [
        "시외우등"
      ]
    },
    "routeId": "939337105205",
    "pattern": {
      "type": "specific-day",
      "days": [
        1,
        2,
        3,
        4,
        5,
        6,
        7
      ]
    }
  },
  {
    "departureTerminalId": "9303",
    "arrivalTerminalId": "1879",
    "durationInMinutes": [
      0
    ],
    "operator": [
      "대원고속"
    ],
    "departureTime": {
      "hour": 23,
      "minute": 50
    },
    "isTemporaryRoute": false,
    "fare": {
      "어른": [
        14500
      ],
      "초등생": [
        7300
      ],
      "중고생": [
        10100
      ]
    },
    "stops": [
      [
        {
          "name": "인천공항(제2터미널)"
        },
        {
          "name": "인천공항"
        },
        {
          "name": "화성세무서"
        },
        {
          "name": "봉담국민체육센터"
        },
        {
          "name": "봉담중심상가"
        },
        {
          "name": "화성에듀시티파라곤"
        },
        {
          "name": "신일해피트리2차"
        },
        {
          "name": "융건릉사거리"
        },
        {
          "name": "우미린2차"
        },
        {
          "name": "향남터미널"
        },
        {
          "name": "안중"
        }
      ]
    ],
    "type": "bus",
    "extra": {
      "seatsAmount": [
        28
      ],
      "busClass": [
        "심야우등1"
      ]
    },
    "routeId": "939337105205",
    "pattern": {
      "type": "specific-day",
      "days": [
        1,
        2,
        3,
        4,
        5,
        6,
        7
      ]
    }
  }
]