[
  {
    "departureTerminalId": "9601",
    "arrivalTerminalId": "6244",
    "durationInMinutes": [
      80
    ],
    "operator": [
      "경산버스㈜"
    ],
    "busClass": [
      "일반"
    ],
    "departureTime": {
      "hour": 12,
      "minute": 20
    },
    "isTemporaryRoute": false,
    "seatsAmount": [
      28
    ],
    "fare": {
      "어른": [
        8800
      ],
      "초등생": [
        4400
      ],
      "중고생": [
        7000
      ]
    },
    "pattern": {
      "type": "everyday"
    }
  }
]